README.md
setup.py
bellybutton/__init__.py
bellybutton/caching.py
bellybutton/cli.py
bellybutton/exceptions.py
bellybutton/initialization.py
bellybutton/linting.py
bellybutton/parsing.py
bellybutton.egg-info/PKG-INFO
bellybutton.egg-info/SOURCES.txt
bellybutton.egg-info/dependency_links.txt
bellybutton.egg-info/entry_points.txt
bellybutton.egg-info/requires.txt
bellybutton.egg-info/top_level.txt