Metadata-Version: 2.1
Name: bellybutton
Version: 0.3.1
Summary: Custom Python linting through AST expressions.
Home-page: https://github.com/hchasestevens/bellybutton
Author: H. Chase Stevens
Author-email: chase@chasestevens.com
License: MIT
Platform: any
Classifier: Programming Language :: Python
Classifier: Programming Language :: Python :: 2
Classifier: Programming Language :: Python :: 2.7
Classifier: Programming Language :: Python :: 3
Classifier: Programming Language :: Python :: 3.6
Classifier: Topic :: Software Development :: Libraries :: Python Modules
Classifier: Intended Audience :: Developers
Classifier: Operating System :: OS Independent
Classifier: License :: OSI Approved :: MIT License
Provides-Extra: dev
